{"stat.chestOpened":1,"stat.useItem.minecraft.bow":1,"stat.walkOneCm":82785,"stat.leaveGame":20,"stat.useItem.minecraft.skull":3,"stat.flyOneCm":576494,"stat.drop":2,"stat.jump":194,"stat.swimOneCm":770,"stat.playOneMinute":60571,"stat.climbOneCm":228,"stat.useItem.minecraft.item_frame":88,"stat.useItem.minecraft.spruce_stairs":1,"stat.crouchOneCm":6179,"stat.timeSinceDeath":60571,"stat.sprintOneCm":32376,"stat.useItem.minecraft.sign":8,"achievement.exploreAllBiomes":{"value":0,"progress":["Beach","Forest","Ocean","Savanna"]},"stat.diveOneCm":3354}